[{"_id": "w5tJmzeeWKBFCuuQW", "postedAt": "2023-01-12T00:26:15.002Z", "postId": "5WwDTpNDYAsXjADAt", "htmlBody": "<p>Ran out of 'Zaps' so if anyone has a paid account...</p>\n", "parentCommentId": null, "user": {"username": "david_reinstein"}}, {"_id": "9bxpYiAv2an4zb7zX", "postedAt": "2023-01-12T03:26:49.719Z", "postId": "5WwDTpNDYAsXjADAt", "htmlBody": "<p>I stayed at an <i>EA House </i>last summer and had a very positive experience (you can read about my positive testimonial <a href=\"https://forum.effectivealtruism.org/posts/8e8NFh6kCHptWurwC/ea-houses-a-positive-testimonial\">here</a>).</p><p>I shared this idea in the original spreadsheet, but I think it deserves more attention: using EA houses or a similar platform to facilitate home exchanges for effective altruists who work remotely.</p><p>There are many effective altruists who work remotely, and many of them would benefit from being able to spend time in different cities, whether for work, community engagement, or personal enjoyment. However, working remotely in new cities can be very expensive, largely due to high accommodation costs.</p><p>At the same time, many people cannot host on EA houses because they only have one room or bed available in their home, which is otherwise occupied when they are at home. By creating a home exchange platform, we can increase the supply of potential places to stay and provide a lot of additional utility for those who would benefit from it.</p>", "parentCommentId": null, "user": {"username": "DMMF"}}, {"_id": "WzJkdot7zDfqmynLy", "postedAt": "2023-01-13T22:38:53.477Z", "postId": "5WwDTpNDYAsXjADAt", "htmlBody": "<p>Update -- added a 'seekers table' for those looking for a place,  you can input yourself <a href=\"https://airtable.com/shrpOdeq1MAw78Peu\">here</a></p>\n", "parentCommentId": null, "user": {"username": "david_reinstein"}}]