[{"_id": "oShnaYtSSLouBdFcS", "postedAt": "2023-12-04T03:19:34.542Z", "postId": "7RStguCHnLPfJTfzz", "htmlBody": "<p>Your question is hard to read and understand the way it's written. Try using a human proofreader or a software tool like <a href=\"https://www.grammarly.com/\">Grammarly</a>.</p>", "parentCommentId": null, "user": {"username": "Yarrow Bouchard"}}, {"_id": "GrPAJnGeEAJBtmXeD", "postedAt": "2023-12-04T04:29:37.375Z", "postId": "7RStguCHnLPfJTfzz", "htmlBody": "<ul><li><strong>Could an AGI like this be easily controlled and monitored?</strong> If it can't hide its plans or talk to other AIs, it would be much easier to keep track of what it's doing. For example, if it wanted to send a command to robots, we would see the command before it's sent because it would have to be changed into a form that the robots can understand.</li></ul>", "parentCommentId": "oShnaYtSSLouBdFcS", "user": {"username": "David turner"}}, {"_id": "Pm5iyt8Sv6HtsudKb", "postedAt": "2023-12-04T04:30:40.399Z", "postId": "7RStguCHnLPfJTfzz", "htmlBody": "<p>i used bard ai.</p>", "parentCommentId": "oShnaYtSSLouBdFcS", "user": {"username": "David turner"}}]