[{"_id": "hK58ijxmcFZYdLigP", "postedAt": "2023-02-20T22:15:46.780Z", "postId": "8XDcMhJ65mwWrouro", "htmlBody": "<p>Very excited to see you're doing this! Have added it to the <a href=\"https://bit.ly/eaadirectory_public\">EAA Community Directory</a> Resources now.</p>", "parentCommentId": null, "user": {"username": "CristinaSchmidtIb\u00e1\u00f1ez"}}, {"_id": "Z2KmGisRWe8hv6rqL", "postedAt": "2023-03-23T13:34:30.246Z", "postId": "8XDcMhJ65mwWrouro", "htmlBody": "<p>Very happy to see this! But for information, the Slack link is expired (if you update it, be careful because it's in multiple places in the article) <a href=\"https://forum.effectivealtruism.org/users/sofiabalderson?mention=user\">@SofiaBalderson</a> &nbsp;<a href=\"https://forum.effectivealtruism.org/users/cameron-k?mention=user\">@Cameron.K</a>&nbsp;</p>", "parentCommentId": null, "user": {"username": "GuillaumeVrx"}}, {"_id": "DM3z2pmzpifpbvGKg", "postedAt": "2023-03-23T13:38:41.457Z", "postId": "8XDcMhJ65mwWrouro", "htmlBody": "<p>Maybe also advertise the Slack in here? <a href=\"https://forum.effectivealtruism.org/groups/wiDFRkBrgfiXrPcmb\">https://forum.effectivealtruism.org/groups/wiDFRkBrgfiXrPcmb</a></p>", "parentCommentId": "Z2KmGisRWe8hv6rqL", "user": {"username": "GuillaumeVrx"}}]