[{"_id": "b7kyCJGL3JWuhnnEk", "postedAt": "2023-12-12T13:17:49.932Z", "postId": "aoWpk28j3W65mYMgy", "htmlBody": "<p><strong>Executive summary</strong>: You can run multiple fellowships per semester by splitting them into parts, like a weekly fellowship plus an intensive one, to onboard more people while minimizing organizational work.</p><p><strong>Key points:</strong></p><ol><li>Running multiple fellowships per semester can engage more people with less work if you reuse materials or combine fellowship types.</li><li>A good approach is a weekly fellowship plus an intensive one joined together for the second half.</li><li>This takes coordination and experience running fellowships, so gauge your team's capacity first.</li><li>Consider whether more frequent fellowships reduce their specialness and your time for other tasks.</li><li>The author hasn't run the ideal combination yet, but will update once iterations happen.</li></ol><p>&nbsp;</p><p>&nbsp;</p><p><i>This comment was auto-generated by the EA Forum Team. Feel free to point out issues with this summary by replying to the comment, and</i><a href=\"https://forum.effectivealtruism.org/contact\"><i>&nbsp;<u>contact us</u></i></a><i> if you have feedback.</i></p>", "parentCommentId": null, "user": {"username": "SummaryBot"}}]