[{"_id": "XwmXmdFk2sKsn32HN", "postedAt": "2014-12-23T03:12:28.122Z", "postId": "b2Mb3xi9wviMKXrK5", "htmlBody": "<p>I would add:</p>\n<ul>\n<li>Consider the scale of the issue (how many people are being harmed or killed by this problem?)</li>\n<li>Consider the tractability of the action (how much difference will this cause actually make toward solving the problem?)</li>\n<li>Consider the room for more funding of an organization (what would this organization do with more money?)</li>\n<li>As a general rule of thumb, aim for the world's worst off individuals</li>\n</ul>\n<p>These are pretty basic but I think most mainstream social causes (e.g. Black Lives Matter, ALS Ice Bucket Challenge) fail to take these considerations into account.</p>\n", "parentCommentId": null, "user": {"username": "Bitton"}}, {"_id": "tJkewTfGAqGz9rJQL", "postedAt": "2018-04-08T14:25:11.183Z", "postId": "b2Mb3xi9wviMKXrK5", "htmlBody": "<p>Based on the report [1], it's a bit misleading to say that they are a charity doing $35 cataracts.  The report seems pretty explicit that donations to the charity are used for other activities.</p>\n", "parentCommentId": null, "user": {"username": "capybaralet"}}]