[{"_id": "fkSbsj2uQuskZsBx8", "postedAt": "2022-10-02T08:13:27.125Z", "postId": "bktDcapniZsRu8tix", "htmlBody": "<p>As a general point, do you believe that if &nbsp;women did realize the full benefits of receiving education in terms of learning outcomes, that then they would be served by their literacy, knowledge of mathematics, physics, politics, government, and software even if they could not find employment in a career field such as engineering?</p><p>Your answer might help me understand your question a little better.</p><p>I am also curious about what expert or organization discusses the relationship between poverty and population that you allude to when you write:</p><blockquote><p>To be clear, I'm aware that most experts no longer believe global overpopulation will be an issue, and I think more population growth could be good for the progress of technology.&nbsp;</p></blockquote>", "parentCommentId": null, "user": {"username": "Noah Scales"}}]