[{"_id": "a5rahkhCRvQ7XeEq9", "postedAt": "2022-12-10T08:46:23.568Z", "postId": "G5tF3TP7btJThcKoJ", "htmlBody": "<blockquote><p>While we don't like putting labels but in the interest of upfront disclosure, our politics can be thought of as somewhere in the anarcho-communist/syndicalist corner, with sympathies for Bookchin<br>[...]<br>Authors background: ML/game theory PhD students who've been thinking about politics, economics and ways to achieve some scalable, feasible approximation to anarchocommunism</p></blockquote><p><br>The authors &nbsp;had my &nbsp;interest when I saw the title of this post, though after I've read the sections quoted above and this <a href=\"https://forum.effectivealtruism.org/posts/G5tF3TP7btJThcKoJ/cause-exploration-prizes-dynamic-democracy-to-guard-against#How_to_strengthen_dynamic_democracy\">entire section of this essay</a>, now <a href=\"https://www.youtube.com/watch?v=gdnbAvnRrQs\">they have my attention</a>.</p>", "parentCommentId": null, "user": {"username": "Evan_Gaensbauer"}}]