[{"_id": "qiq7DZXxexNwnBSSf", "postedAt": "2022-10-25T04:36:11.315Z", "postId": "Hi5z6tm9d2keHALgv", "htmlBody": "<p>Thanks for including my post here. Your summary is shockingly good! It captures the essence of my article very well.</p>\n<p>For the record I'll note that not all the \u2018bad\u2019 things the hiring consultants had planned actually happened. Because the manager at the org that was hiring did some reading and then took over the process.</p>\n", "parentCommentId": null, "user": {"username": "rmoehn"}}, {"_id": "kL9sq4uhtA9wJpvKb", "postedAt": "2022-10-31T02:43:17.125Z", "postId": "Hi5z6tm9d2keHALgv", "htmlBody": "<p>Great to hear, and thanks for the clarification.</p>", "parentCommentId": "qiq7DZXxexNwnBSSf", "user": {"username": "GreyArea"}}]